[{"Handles":["-------"],"NPM(K)":["------"],"PM(K)":["-----"],"WS(K)":["-----"],"CPU(s)":["------"],"Id":["--"],"SI":["--"],"ProcessName":["-----------"]},{"Handles":["99"],"NPM(K)":["8"],"PM(K)":["2688"],"WS(K)":["4860"],"CPU(s)":["0"],"Id":["4048"],"SI":["0"],"ProcessName":["ACCSvc"]},{"Handles":["91"],"NPM(K)":["6"],"PM(K)":["1404"],"WS(K)":["5096"],"CPU(s)":["0"],"Id":["4884"],"SI":["0"],"ProcessName":["AggregatorHost"]},{"Handles":["172"],"NPM(K)":["12"],"PM(K)":["3872"],"WS(K)":["6472"],"CPU(s)":["0"],"Id":["2664"],"SI":["0"],"ProcessName":["amdfendrsr"]},{"Handles":["245"],"NPM(K)":["13"],"PM(K)":["2436"],"WS(K)":["11076"],"CPU(s)":["0"],"Id":["13268"],"SI":["6"],"ProcessName":["atieclxx"]},{"Handles":["180"],"NPM(K)":["9"],"PM(K)":["1520"],"WS(K)":["5620"],"CPU(s)":["0"],"Id":["2680"],"SI":["0"],"ProcessName":["atiesrxx"]},{"Handles":["314"],"NPM(K)":["20"],"PM(K)":["32020"],"WS(K)":["26512"],"CPU(s)":["0"],"Id":["8676"],"SI":["0"],"ProcessName":["CamUsage"]},{"Handles":["82"],"NPM(K)":["7"],"PM(K)":["5256"],"WS(K)":["4064"],"CPU(s)":["0"],"Id":["3864"],"SI":["0"],"ProcessName":["conhost"]},{"Handles":["634"],"NPM(K)":["24"],"PM(K)":["2092"],"WS(K)":["5384"],"CPU(s)":["0"],"Id":["940"],"SI":["0"],"ProcessName":["csrss"]},{"Handles":["822"],"NPM(K)":["34"],"PM(K)":["3944"],"WS(K)":["8336"],"CPU(s)":["0"],"Id":["7152"],"SI":["6"],"ProcessName":["csrss"]},{"Handles":["201"],"NPM(K)":["18"],"PM(K)":["3608"],"WS(K)":["10892"],"CPU(s)":["0"],"Id":["9676"],"SI":["0"],"ProcessName":["dllhost"]},{"Handles":["1353"],"NPM(K)":["84"],"PM(K)":["162712"],"WS(K)":["140968"],"CPU(s)":["0"],"Id":["12416"],"SI":["6"],"ProcessName":["dwm"]},{"Handles":["37"],"NPM(K)":["6"],"PM(K)":["1592"],"WS(K)":["2444"],"CPU(s)":["0"],"Id":["1308"],"SI":["0"],"ProcessName":["fontdrvhost"]},{"Handles":["37"],"NPM(K)":["10"],"PM(K)":["4664"],"WS(K)":["8092"],"CPU(s)":["0"],"Id":["12708"],"SI":["6"],"ProcessName":["fontdrvhost"]},{"Handles":["130"],"NPM(K)":["7"],"PM(K)":["1292"],"WS(K)":["4872"],"CPU(s)":["0"],"Id":["4032"],"SI":["0"],"ProcessName":["gameinputsvc"]},{"Handles":["280"],"NPM(K)":["13"],"PM(K)":["3296"],"WS(K)":["17592"],"CPU(s)":["0"],"Id":["14224"],"SI":["6"],"ProcessName":["gameinputsvc"]},{"Handles":["679"],"NPM(K)":["28"],"PM(K)":["9792"],"WS(K)":["34476"],"CPU(s)":["0"],"Id":["4752"],"SI":["0"],"ProcessName":["gamingservices"]},{"Handles":["116"],"NPM(K)":["7"],"PM(K)":["1128"],"WS(K)":["4472"],"CPU(s)":["0"],"Id":["4680"],"SI":["0"],"ProcessName":["gamingservicesnet"]},{"Handles":["0"],"NPM(K)":["0"],"PM(K)":["60"],"WS(K)":["8"],"CPU(s)":["0"],"Id":["0"],"SI":["0"],"ProcessName":["Idle"]},{"Handles":["55"],"NPM(K)":["10"],"PM(K)":["1496"],"WS(K)":["3044"],"CPU(s)":["0"],"Id":["1148"],"SI":["0"],"ProcessName":["LsaIso"]},{"Handles":["1599"],"NPM(K)":["27"],"PM(K)":["8780"],"WS(K)":["21904"],"CPU(s)":["0"],"Id":["1156"],"SI":["0"],"ProcessName":["lsass"]},{"Handles":["0"],"NPM(K)":["0"],"PM(K)":["1272"],"WS(K)":["227088"],"CPU(s)":["0"],"Id":["2308"],"SI":["0"],"ProcessName":["Memory","Compression"]},{"Handles":["294"],"NPM(K)":["19"],"PM(K)":["31472"],"WS(K)":["25560"],"CPU(s)":["0"],"Id":["8672"],"SI":["0"],"ProcessName":["MicUsage"]},{"Handles":["107"],"NPM(K)":["8"],"PM(K)":["1960"],"WS(K)":["5952"],"CPU(s)":["0"],"Id":["13244"],"SI":["0"],"ProcessName":["MpCopyAccelerator"]},{"Handles":["947"],"NPM(K)":["108"],"PM(K)":["299212"],"WS(K)":["228152"],"CPU(s)":["0"],"Id":["4132"],"SI":["0"],"ProcessName":["MsMpEng"]},{"Handles":["218"],"NPM(K)":["13"],"PM(K)":["3964"],"WS(K)":["10260"],"CPU(s)":["0"],"Id":["1144"],"SI":["0"],"ProcessName":["NisSrv"]},{"Handles":["822"],"NPM(K)":["28"],"PM(K)":["42436"],"WS(K)":["37928"],"CPU(s)":["0"],"Id":["3204"],"SI":["0"],"ProcessName":["OfficeClickToRun"]},{"Handles":["244"],"NPM(K)":["15"],"PM(K)":["24432"],"WS(K)":["18556"],"CPU(s)":["0"],"Id":["10084"],"SI":["6"],"ProcessName":["QAAdminAgent"]},{"Handles":["300"],"NPM(K)":["11"],"PM(K)":["3284"],"WS(K)":["9232"],"CPU(s)":["0"],"Id":["11668"],"SI":["0"],"ProcessName":["QASvc"]},{"Handles":["0"],"NPM(K)":["16"],"PM(K)":["7248"],"WS(K)":["56896"],"CPU(s)":["0"],"Id":["168"],"SI":["0"],"ProcessName":["Registry"]},{"Handles":["332"],"NPM(K)":["23"],"PM(K)":["3376"],"WS(K)":["9484"],"CPU(s)":["0"],"Id":["2316"],"SI":["0"],"ProcessName":["RtkAudUService64"]},{"Handles":["883"],"NPM(K)":["76"],"PM(K)":["35716"],"WS(K)":["40784"],"CPU(s)":["0"],"Id":["7624"],"SI":["0"],"ProcessName":["SearchIndexer"]},{"Handles":["0"],"NPM(K)":["0"],"PM(K)":["184"],"WS(K)":["29392"],"CPU(s)":["0"],"Id":["104"],"SI":["0"],"ProcessName":["Secure","System"]},{"Handles":["457"],"NPM(K)":["18"],"PM(K)":["6996"],"WS(K)":["15204"],"CPU(s)":["0"],"Id":["9012"],"SI":["0"],"ProcessName":["SecurityHealthService"]},{"Handles":["790"],"NPM(K)":["16"],"PM(K)":["6416"],"WS(K)":["14108"],"CPU(s)":["0"],"Id":["1064"],"SI":["0"],"ProcessName":["services"]},{"Handles":["119"],"NPM(K)":["8"],"PM(K)":["8336"],"WS(K)":["8868"],"CPU(s)":["0"],"Id":["1784"],"SI":["0"],"ProcessName":["SgrmBroker"]},{"Handles":["57"],"NPM(K)":["4"],"PM(K)":["1096"],"WS(K)":["1084"],"CPU(s)":["0"],"Id":["512"],"SI":["0"],"ProcessName":["smss"]},{"Handles":["431"],"NPM(K)":["21"],"PM(K)":["5504"],"WS(K)":["11336"],"CPU(s)":["0"],"Id":["3720"],"SI":["0"],"ProcessName":["spoolsv"]},{"Handles":["152"],"NPM(K)":["26"],"PM(K)":["5208"],"WS(K)":["8016"],"CPU(s)":["0"],"Id":["1184"],"SI":["0"],"ProcessName":["svchost"]},{"Handles":["1898"],"NPM(K)":["26"],"PM(K)":["15328"],"WS(K)":["37768"],"CPU(s)":["0"],"Id":["1280"],"SI":["0"],"ProcessName":["svchost"]},{"Handles":["1381"],"NPM(K)":["21"],"PM(K)":["11796"],"WS(K)":["17680"],"CPU(s)":["0"],"Id":["1424"],"SI":["0"],"ProcessName":["svchost"]},{"Handles":["373"],"NPM(K)":["12"],"PM(K)":["3192"],"WS(K)":["8504"],"CPU(s)":["0"],"Id":["1464"],"SI":["0"],"ProcessName":["svchost"]},{"Handles":["437"],"NPM(K)":["19"],"PM(K)":["6520"],"WS(K)":["17088"],"CPU(s)":["0"],"Id":["1540"],"SI":["0"],"ProcessName":["svchost"]},{"Handles":["103"],"NPM(K)":["10"],"PM(K)":["1140"],"WS(K)":["4888"],"CPU(s)":["0"],"Id":["1600"],"SI":["0"],"ProcessName":["svchost"]},{"Handles":["261"],"NPM(K)":["13"],"PM(K)":["2628"],"WS(K)":["9380"],"CPU(s)":["0"],"Id":["1692"],"SI":["0"],"ProcessName":["svchost"]},{"Handles":["221"],"NPM(K)":["12"],"PM(K)":["2828"],"WS(K)":["10892"],"CPU(s)":["0"],"Id":["1708"],"SI":["0"],"ProcessName":["svchost"]},{"Handles":["678"],"NPM(K)":["10"],"PM(K)":["2312"],"WS(K)":["11692"],"CPU(s)":["0"],"Id":["1712"],"SI":["0"],"ProcessName":["svchost"]},{"Handles":["182"],"NPM(K)":["11"],"PM(K)":["2076"],"WS(K)":["8444"],"CPU(s)":["0"],"Id":["1724"],"SI":["0"],"ProcessName":["svchost"]},{"Handles":["188"],"NPM(K)":["11"],"PM(K)":["2156"],"WS(K)":["11824"],"CPU(s)":["0"],"Id":["1732"],"SI":["0"],"ProcessName":["svchost"]},{"Handles":["439"],"NPM(K)":["18"],"PM(K)":["6880"],"WS(K)":["15640"],"CPU(s)":["0"],"Id":["1848"],"SI":["0"],"ProcessName":["svchost"]},{"Handles":["365"],"NPM(K)":["12"],"PM(K)":["2868"],"WS(K)":["8420"],"CPU(s)":["0"],"Id":["1912"],"SI":["0"],"ProcessName":["svchost"]},{"Handles":["197"],"NPM(K)":["11"],"PM(K)":["2916"],"WS(K)":["9444"],"CPU(s)":["0"],"Id":["1920"],"SI":["0"],"ProcessName":["svchost"]},{"Handles":["187"],"NPM(K)":["8"],"PM(K)":["2272"],"WS(K)":["5924"],"CPU(s)":["0"],"Id":["1976"],"SI":["0"],"ProcessName":["svchost"]},{"Handles":["277"],"NPM(K)":["11"],"PM(K)":["3392"],"WS(K)":["11440"],"CPU(s)":["0"],"Id":["2120"],"SI":["0"],"ProcessName":["svchost"]},{"Handles":["920"],"NPM(K)":["21"],"PM(K)":["7028"],"WS(K)":["15564"],"CPU(s)":["0"],"Id":["2168"],"SI":["0"],"ProcessName":["svchost"]},{"Handles":["258"],"NPM(K)":["13"],"PM(K)":["5008"],"WS(K)":["14756"],"CPU(s)":["0"],"Id":["2276"],"SI":["0"],"ProcessName":["svchost"]},{"Handles":["177"],"NPM(K)":["10"],"PM(K)":["1712"],"WS(K)":["7136"],"CPU(s)":["0"],"Id":["2444"],"SI":["0"],"ProcessName":["svchost"]},{"Handles":["115"],"NPM(K)":["8"],"PM(K)":["1448"],"WS(K)":["6000"],"CPU(s)":["0"],"Id":["2588"],"SI":["0"],"ProcessName":["svchost"]},{"Handles":["202"],"NPM(K)":["11"],"PM(K)":["2032"],"WS(K)":["8648"],"CPU(s)":["0"],"Id":["2628"],"SI":["0"],"ProcessName":["svchost"]},{"Handles":["463"],"NPM(K)":["14"],"PM(K)":["17476"],"WS(K)":["16024"],"CPU(s)":["0"],"Id":["2652"],"SI":["0"],"ProcessName":["svchost"]},{"Handles":["296"],"NPM(K)":["14"],"PM(K)":["3860"],"WS(K)":["8436"],"CPU(s)":["0"],"Id":["2672"],"SI":["0"],"ProcessName":["svchost"]},{"Handles":["237"],"NPM(K)":["13"],"PM(K)":["2712"],"WS(K)":["14148"],"CPU(s)":["0"],"Id":["3020"],"SI":["0"],"ProcessName":["svchost"]},{"Handles":["282"],"NPM(K)":["8"],"PM(K)":["1308"],"WS(K)":["5468"],"CPU(s)":["0"],"Id":["3028"],"SI":["0"],"ProcessName":["svchost"]},{"Handles":["170"],"NPM(K)":["9"],"PM(K)":["1888"],"WS(K)":["6748"],"CPU(s)":["0"],"Id":["3036"],"SI":["0"],"ProcessName":["svchost"]},{"Handles":["177"],"NPM(K)":["13"],"PM(K)":["1908"],"WS(K)":["7492"],"CPU(s)":["0"],"Id":["3080"],"SI":["0"],"ProcessName":["svchost"]},{"Handles":["233"],"NPM(K)":["11"],"PM(K)":["2376"],"WS(K)":["8160"],"CPU(s)":["0"],"Id":["3112"],"SI":["0"],"ProcessName":["svchost"]},{"Handles":["174"],"NPM(K)":["11"],"PM(K)":["1988"],"WS(K)":["7628"],"CPU(s)":["0"],"Id":["3120"],"SI":["0"],"ProcessName":["svchost"]},{"Handles":["128"],"NPM(K)":["9"],"PM(K)":["1332"],"WS(K)":["5400"],"CPU(s)":["0"],"Id":["3248"],"SI":["0"],"ProcessName":["svchost"]},{"Handles":["519"],"NPM(K)":["14"],"PM(K)":["4108"],"WS(K)":["14996"],"CPU(s)":["0"],"Id":["3256"],"SI":["0"],"ProcessName":["svchost"]},{"Handles":["414"],"NPM(K)":["13"],"PM(K)":["2936"],"WS(K)":["8760"],"CPU(s)":["0"],"Id":["3344"],"SI":["0"],"ProcessName":["svchost"]},{"Handles":["236"],"NPM(K)":["11"],"PM(K)":["3348"],"WS(K)":["7220"],"CPU(s)":["0"],"Id":["3348"],"SI":["0"],"ProcessName":["svchost"]},{"Handles":["152"],"NPM(K)":["9"],"PM(K)":["1728"],"WS(K)":["6136"],"CPU(s)":["0"],"Id":["3352"],"SI":["0"],"ProcessName":["svchost"]},{"Handles":["312"],"NPM(K)":["11"],"PM(K)":["14432"],"WS(K)":["19736"],"CPU(s)":["0"],"Id":["3444"],"SI":["0"],"ProcessName":["svchost"]},{"Handles":["186"],"NPM(K)":["10"],"PM(K)":["2052"],"WS(K)":["7052"],"CPU(s)":["0"],"Id":["3532"],"SI":["0"],"ProcessName":["svchost"]},{"Handles":["529"],"NPM(K)":["26"],"PM(K)":["6816"],"WS(K)":["17088"],"CPU(s)":["0"],"Id":["3620"],"SI":["0"],"ProcessName":["svchost"]},{"Handles":["236"],"NPM(K)":["14"],"PM(K)":["3088"],"WS(K)":["13640"],"CPU(s)":["0"],"Id":["3644"],"SI":["0"],"ProcessName":["svchost"]},{"Handles":["496"],"NPM(K)":["34"],"PM(K)":["11104"],"WS(K)":["16968"],"CPU(s)":["0"],"Id":["3748"],"SI":["0"],"ProcessName":["svchost"]},{"Handles":["407"],"NPM(K)":["20"],"PM(K)":["4692"],"WS(K)":["20224"],"CPU(s)":["0"],"Id":["3868"],"SI":["0"],"ProcessName":["svchost"]},{"Handles":["149"],"NPM(K)":["10"],"PM(K)":["3484"],"WS(K)":["11548"],"CPU(s)":["0"],"Id":["3876"],"SI":["0"],"ProcessName":["svchost"]},{"Handles":["177"],"NPM(K)":["10"],"PM(K)":["1864"],"WS(K)":["7040"],"CPU(s)":["0"],"Id":["3900"],"SI":["0"],"ProcessName":["svchost"]},{"Handles":["605"],"NPM(K)":["26"],"PM(K)":["19512"],"WS(K)":["30804"],"CPU(s)":["0"],"Id":["4008"],"SI":["0"],"ProcessName":["svchost"]},{"Handles":["378"],"NPM(K)":["21"],"PM(K)":["28884"],"WS(K)":["35936"],"CPU(s)":["0"],"Id":["4024"],"SI":["0"],"ProcessName":["svchost"]},{"Handles":["294"],"NPM(K)":["28"],"PM(K)":["4256"],"WS(K)":["13748"],"CPU(s)":["0"],"Id":["4040"],"SI":["0"],"ProcessName":["svchost"]},{"Handles":["274"],"NPM(K)":["15"],"PM(K)":["2756"],"WS(K)":["7332"],"CPU(s)":["0"],"Id":["4072"],"SI":["0"],"ProcessName":["svchost"]},{"Handles":["368"],"NPM(K)":["20"],"PM(K)":["2972"],"WS(K)":["9464"],"CPU(s)":["0"],"Id":["4080"],"SI":["0"],"ProcessName":["svchost"]},{"Handles":["735"],"NPM(K)":["18"],"PM(K)":["9544"],"WS(K)":["17044"],"CPU(s)":["0"],"Id":["4100"],"SI":["0"],"ProcessName":["svchost"]},{"Handles":["206"],"NPM(K)":["12"],"PM(K)":["2372"],"WS(K)":["8548"],"CPU(s)":["0"],"Id":["4536"],"SI":["0"],"ProcessName":["svchost"]},{"Handles":["238"],"NPM(K)":["11"],"PM(K)":["2256"],"WS(K)":["7536"],"CPU(s)":["0"],"Id":["5076"],"SI":["0"],"ProcessName":["svchost"]},{"Handles":["201"],"NPM(K)":["13"],"PM(K)":["1716"],"WS(K)":["7356"],"CPU(s)":["0"],"Id":["5100"],"SI":["0"],"ProcessName":["svchost"]},{"Handles":["332"],"NPM(K)":["13"],"PM(K)":["4748"],"WS(K)":["11060"],"CPU(s)":["0"],"Id":["5188"],"SI":["0"],"ProcessName":["svchost"]},{"Handles":["384"],"NPM(K)":["13"],"PM(K)":["2864"],"WS(K)":["13064"],"CPU(s)":["0"],"Id":["5376"],"SI":["0"],"ProcessName":["svchost"]},{"Handles":["116"],"NPM(K)":["8"],"PM(K)":["1316"],"WS(K)":["5348"],"CPU(s)":["0"],"Id":["5708"],"SI":["0"],"ProcessName":["svchost"]},{"Handles":["288"],"NPM(K)":["15"],"PM(K)":["6136"],"WS(K)":["22876"],"CPU(s)":["0"],"Id":["5712"],"SI":["0"],"ProcessName":["svchost"]},{"Handles":["462"],"NPM(K)":["22"],"PM(K)":["6060"],"WS(K)":["20308"],"CPU(s)":["0"],"Id":["5724"],"SI":["0"],"ProcessName":["svchost"]},{"Handles":["166"],"NPM(K)":["10"],"PM(K)":["1828"],"WS(K)":["7836"],"CPU(s)":["0"],"Id":["5972"],"SI":["0"],"ProcessName":["svchost"]},{"Handles":["86"],"NPM(K)":["6"],"PM(K)":["1008"],"WS(K)":["4116"],"CPU(s)":["0"],"Id":["6396"],"SI":["0"],"ProcessName":["svchost"]},{"Handles":["267"],"NPM(K)":["14"],"PM(K)":["3388"],"WS(K)":["13760"],"CPU(s)":["0"],"Id":["6976"],"SI":["0"],"ProcessName":["svchost"]},{"Handles":["266"],"NPM(K)":["15"],"PM(K)":["3648"],"WS(K)":["16728"],"CPU(s)":["0"],"Id":["7392"],"SI":["0"],"ProcessName":["svchost"]},{"Handles":["212"],"NPM(K)":["15"],"PM(K)":["2028"],"WS(K)":["6840"],"CPU(s)":["0"],"Id":["7464"],"SI":["0"],"ProcessName":["svchost"]},{"Handles":["199"],"NPM(K)":["15"],"PM(K)":["6636"],"WS(K)":["9524"],"CPU(s)":["0"],"Id":["7892"],"SI":["0"],"ProcessName":["svchost"]},{"Handles":["222"],"NPM(K)":["13"],"PM(K)":["2656"],"WS(K)":["9328"],"CPU(s)":["0"],"Id":["8332"],"SI":["0"],"ProcessName":["svchost"]},{"Handles":["7865"],"NPM(K)":["20"],"PM(K)":["24652"],"WS(K)":["25600"],"CPU(s)":["0"],"Id":["8440"],"SI":["0"],"ProcessName":["svchost"]},{"Handles":["311"],"NPM(K)":["17"],"PM(K)":["4304"],"WS(K)":["22032"],"CPU(s)":["0"],"Id":["9000"],"SI":["0"],"ProcessName":["svchost"]},{"Handles":["148"],"NPM(K)":["42"],"PM(K)":["1676"],"WS(K)":["6396"],"CPU(s)":["0"],"Id":["9232"],"SI":["0"],"ProcessName":["svchost"]},{"Handles":["447"],"NPM(K)":["25"],"PM(K)":["3564"],"WS(K)":["11648"],"CPU(s)":["0"],"Id":["10272"],"SI":["0"],"ProcessName":["svchost"]},{"Handles":["295"],"NPM(K)":["16"],"PM(K)":["3404"],"WS(K)":["14532"],"CPU(s)":["0"],"Id":["11808"],"SI":["0"],"ProcessName":["svchost"]},{"Handles":["383"],"NPM(K)":["20"],"PM(K)":["7480"],"WS(K)":["25708"],"CPU(s)":["0"],"Id":["11872"],"SI":["0"],"ProcessName":["svchost"]},{"Handles":["117"],"NPM(K)":["10"],"PM(K)":["1532"],"WS(K)":["6076"],"CPU(s)":["0"],"Id":["12808"],"SI":["0"],"ProcessName":["svchost"]},{"Handles":["234"],"NPM(K)":["13"],"PM(K)":["2856"],"WS(K)":["12956"],"CPU(s)":["0"],"Id":["15972"],"SI":["0"],"ProcessName":["svchost"]},{"Handles":["4749"],"NPM(K)":["0"],"PM(K)":["48"],"WS(K)":["5328"],"CPU(s)":["0"],"Id":["4"],"SI":["0"],"ProcessName":["System"]},{"Handles":["568"],"NPM(K)":["30"],"PM(K)":["30484"],"WS(K)":["43832"],"CPU(s)":["0"],"Id":["2556"],"SI":["0"],"ProcessName":["UBTService"]},{"Handles":["133"],"NPM(K)":["9"],"PM(K)":["1808"],"WS(K)":["8564"],"CPU(s)":["0"],"Id":["5588"],"SI":["6"],"ProcessName":["unsecapp"]},{"Handles":["163"],"NPM(K)":["11"],"PM(K)":["1484"],"WS(K)":["6072"],"CPU(s)":["0"],"Id":["556"],"SI":["0"],"ProcessName":["wininit"]},{"Handles":["266"],"NPM(K)":["12"],"PM(K)":["2648"],"WS(K)":["9668"],"CPU(s)":["0"],"Id":["12232"],"SI":["6"],"ProcessName":["winlogon"]},{"Handles":["111"],"NPM(K)":["8"],"PM(K)":["1252"],"WS(K)":["4916"],"CPU(s)":["0"],"Id":["3856"],"SI":["0"],"ProcessName":["wlanext"]},{"Handles":["403"],"NPM(K)":["18"],"PM(K)":["15516"],"WS(K)":["21972"],"CPU(s)":["0"],"Id":["8652"],"SI":["0"],"ProcessName":["WmiPrvSE"]},{"Handles":["303"],"NPM(K)":["14"],"PM(K)":["4092"],"WS(K)":["10728"],"CPU(s)":["0"],"Id":["11608"],"SI":["0"],"ProcessName":["WmiPrvSE"]},{"Handles":["80"],"NPM(K)":["6"],"PM(K)":["2624"],"WS(K)":["4720"],"CPU(s)":["0.02"],"Id":["4412"],"SI":["6"],"ProcessName":["cmd"]},{"Handles":["80"],"NPM(K)":["6"],"PM(K)":["2820"],"WS(K)":["4760"],"CPU(s)":["0.02"],"Id":["7652"],"SI":["6"],"ProcessName":["cmd"]},{"Handles":["80"],"NPM(K)":["6"],"PM(K)":["2808"],"WS(K)":["4768"],"CPU(s)":["0.03"],"Id":["1188"],"SI":["6"],"ProcessName":["cmd"]},{"Handles":["80"],"NPM(K)":["6"],"PM(K)":["2620"],"WS(K)":["4712"],"CPU(s)":["0.03"],"Id":["15364"],"SI":["6"],"ProcessName":["cmd"]},{"Handles":["127"],"NPM(K)":["10"],"PM(K)":["1924"],"WS(K)":["9772"],"CPU(s)":["0.03"],"Id":["11616"],"SI":["6"],"ProcessName":["UserOOBEBroker"]},{"Handles":["273"],"NPM(K)":["13"],"PM(K)":["10724"],"WS(K)":["23236"],"CPU(s)":["0.05"],"Id":["8412"],"SI":["6"],"ProcessName":["Code"]},{"Handles":["104"],"NPM(K)":["8"],"PM(K)":["1256"],"WS(K)":["6588"],"CPU(s)":["0.05"],"Id":["16168"],"SI":["6"],"ProcessName":["conhost"]},{"Handles":["175"],"NPM(K)":["10"],"PM(K)":["1868"],"WS(K)":["9644"],"CPU(s)":["0.05"],"Id":["10588"],"SI":["6"],"ProcessName":["SecurityHealthSystray"]},{"Handles":["130"],"NPM(K)":["8"],"PM(K)":["1824"],"WS(K)":["6876"],"CPU(s)":["0.06"],"Id":["4984"],"SI":["6"],"ProcessName":["svchost"]},{"Handles":["154"],"NPM(K)":["9"],"PM(K)":["2156"],"WS(K)":["8600"],"CPU(s)":["0.08"],"Id":["14548"],"SI":["6"],"ProcessName":["svchost"]},{"Handles":["119"],"NPM(K)":["8"],"PM(K)":["1640"],"WS(K)":["10816"],"CPU(s)":["0.09"],"Id":["6720"],"SI":["6"],"ProcessName":["dllhost"]},{"Handles":["145"],"NPM(K)":["10"],"PM(K)":["1980"],"WS(K)":["6440"],"CPU(s)":["0.09"],"Id":["10168"],"SI":["6"],"ProcessName":["msedgewebview2"]},{"Handles":["218"],"NPM(K)":["13"],"PM(K)":["2808"],"WS(K)":["16340"],"CPU(s)":["0.11"],"Id":["8220"],"SI":["6"],"ProcessName":["dllhost"]},{"Handles":["485"],"NPM(K)":["10"],"PM(K)":["2164"],"WS(K)":["7668"],"CPU(s)":["0.11"],"Id":["3012"],"SI":["6"],"ProcessName":["msedge"]},{"Handles":["204"],"NPM(K)":["14"],"PM(K)":["7816"],"WS(K)":["1600"],"CPU(s)":["0.11"],"Id":["2508"],"SI":["6"],"ProcessName":["msedgewebview2"]},{"Handles":["139"],"NPM(K)":["10"],"PM(K)":["2104"],"WS(K)":["10144"],"CPU(s)":["0.11"],"Id":["6252"],"SI":["6"],"ProcessName":["RuntimeBroker"]},{"Handles":["131"],"NPM(K)":["9"],"PM(K)":["1704"],"WS(K)":["8660"],"CPU(s)":["0.17"],"Id":["13596"],"SI":["6"],"ProcessName":["dllhost"]},{"Handles":["337"],"NPM(K)":["18"],"PM(K)":["5504"],"WS(K)":["16792"],"CPU(s)":["0.19"],"Id":["16376"],"SI":["6"],"ProcessName":["taskhostw"]},{"Handles":["259"],"NPM(K)":["16"],"PM(K)":["21596"],"WS(K)":["6044"],"CPU(s)":["0.23"],"Id":["4508"],"SI":["6"],"ProcessName":["msedge"]},{"Handles":["270"],"NPM(K)":["17"],"PM(K)":["21260"],"WS(K)":["45764"],"CPU(s)":["0.25"],"Id":["17400"],"SI":["6"],"ProcessName":["msedge"]},{"Handles":["152"],"NPM(K)":["12"],"PM(K)":["7312"],"WS(K)":["8196"],"CPU(s)":["0.27"],"Id":["8396"],"SI":["6"],"ProcessName":["CodeSetup-stable-6261075646f055b99068d3688932416f2346dd3b"]},{"Handles":["259"],"NPM(K)":["16"],"PM(K)":["17220"],"WS(K)":["5980"],"CPU(s)":["0.27"],"Id":["4124"],"SI":["6"],"ProcessName":["msedge"]},{"Handles":["256"],"NPM(K)":["16"],"PM(K)":["22156"],"WS(K)":["50664"],"CPU(s)":["0.27"],"Id":["12444"],"SI":["6"],"ProcessName":["msedge"]},{"Handles":["165"],"NPM(K)":["10"],"PM(K)":["2220"],"WS(K)":["10208"],"CPU(s)":["0.28"],"Id":["11224"],"SI":["6"],"ProcessName":["svchost"]},{"Handles":["259"],"NPM(K)":["16"],"PM(K)":["17668"],"WS(K)":["6652"],"CPU(s)":["0.33"],"Id":["2184"],"SI":["6"],"ProcessName":["msedge"]},{"Handles":["259"],"NPM(K)":["16"],"PM(K)":["17216"],"WS(K)":["5920"],"CPU(s)":["0.34"],"Id":["12772"],"SI":["6"],"ProcessName":["msedge"]},{"Handles":["261"],"NPM(K)":["16"],"PM(K)":["17472"],"WS(K)":["6248"],"CPU(s)":["0.36"],"Id":["10872"],"SI":["6"],"ProcessName":["msedge"]},{"Handles":["263"],"NPM(K)":["17"],"PM(K)":["17392"],"WS(K)":["6116"],"CPU(s)":["0.39"],"Id":["14936"],"SI":["6"],"ProcessName":["msedge"]},{"Handles":["259"],"NPM(K)":["16"],"PM(K)":["21752"],"WS(K)":["6200"],"CPU(s)":["0.44"],"Id":["7896"],"SI":["6"],"ProcessName":["msedge"]},{"Handles":["294"],"NPM(K)":["16"],"PM(K)":["23628"],"WS(K)":["6512"],"CPU(s)":["0.44"],"Id":["12956"],"SI":["6"],"ProcessName":["msedge"]},{"Handles":["261"],"NPM(K)":["16"],"PM(K)":["21676"],"WS(K)":["6084"],"CPU(s)":["0.45"],"Id":["14468"],"SI":["6"],"ProcessName":["msedge"]},{"Handles":["282"],"NPM(K)":["16"],"PM(K)":["18836"],"WS(K)":["7064"],"CPU(s)":["0.45"],"Id":["16272"],"SI":["6"],"ProcessName":["msedge"]},{"Handles":["197"],"NPM(K)":["44"],"PM(K)":["17624"],"WS(K)":["35468"],"CPU(s)":["0.45"],"Id":["15204"],"SI":["6"],"ProcessName":["node"]},{"Handles":["261"],"NPM(K)":["16"],"PM(K)":["17916"],"WS(K)":["6996"],"CPU(s)":["0.50"],"Id":["15628"],"SI":["6"],"ProcessName":["msedge"]},{"Handles":["112"],"NPM(K)":["8"],"PM(K)":["1396"],"WS(K)":["6340"],"CPU(s)":["0.52"],"Id":["13912"],"SI":["6"],"ProcessName":["conhost"]},{"Handles":["254"],"NPM(K)":["17"],"PM(K)":["8180"],"WS(K)":["19156"],"CPU(s)":["0.53"],"Id":["1556"],"SI":["6"],"ProcessName":["msedge"]},{"Handles":["259"],"NPM(K)":["16"],"PM(K)":["22220"],"WS(K)":["6756"],"CPU(s)":["0.55"],"Id":["2488"],"SI":["6"],"ProcessName":["msedge"]},{"Handles":["259"],"NPM(K)":["16"],"PM(K)":["22228"],"WS(K)":["6724"],"CPU(s)":["0.55"],"Id":["12088"],"SI":["6"],"ProcessName":["msedge"]},{"Handles":["282"],"NPM(K)":["16"],"PM(K)":["19324"],"WS(K)":["7172"],"CPU(s)":["0.56"],"Id":["11876"],"SI":["6"],"ProcessName":["msedge"]},{"Handles":["607"],"NPM(K)":["27"],"PM(K)":["54152"],"WS(K)":["45644"],"CPU(s)":["0.58"],"Id":["10592"],"SI":["6"],"ProcessName":["powershell"]},{"Handles":["316"],"NPM(K)":["16"],"PM(K)":["25624"],"WS(K)":["8508"],"CPU(s)":["0.66"],"Id":["6336"],"SI":["6"],"ProcessName":["msedge"]},{"Handles":["341"],"NPM(K)":["22"],"PM(K)":["2864"],"WS(K)":["11792"],"CPU(s)":["0.67"],"Id":["7432"],"SI":["6"],"ProcessName":["RtkAudUService64"]},{"Handles":["186"],"NPM(K)":["11"],"PM(K)":["2472"],"WS(K)":["13856"],"CPU(s)":["0.69"],"Id":["13232"],"SI":["6"],"ProcessName":["svchost"]},{"Handles":["188"],"NPM(K)":["13"],"PM(K)":["22388"],"WS(K)":["59548"],"CPU(s)":["0.70"],"Id":["8508"],"SI":["6"],"ProcessName":["Code"]},{"Handles":["272"],"NPM(K)":["16"],"PM(K)":["23236"],"WS(K)":["6820"],"CPU(s)":["0.70"],"Id":["13608"],"SI":["6"],"ProcessName":["msedge"]},{"Handles":["270"],"NPM(K)":["16"],"PM(K)":["22900"],"WS(K)":["6448"],"CPU(s)":["0.72"],"Id":["9184"],"SI":["6"],"ProcessName":["msedge"]},{"Handles":["141"],"NPM(K)":["11"],"PM(K)":["1792"],"WS(K)":["9320"],"CPU(s)":["0.72"],"Id":["6296"],"SI":["6"],"ProcessName":["QAAgent"]},{"Handles":["264"],"NPM(K)":["16"],"PM(K)":["19332"],"WS(K)":["7712"],"CPU(s)":["0.73"],"Id":["15632"],"SI":["6"],"ProcessName":["msedge"]},{"Handles":["477"],"NPM(K)":["27"],"PM(K)":["53748"],"WS(K)":["61984"],"CPU(s)":["0.78"],"Id":["15716"],"SI":["6"],"ProcessName":["powershell"]},{"Handles":["272"],"NPM(K)":["29"],"PM(K)":["7912"],"WS(K)":["17748"],"CPU(s)":["0.80"],"Id":["11108"],"SI":["6"],"ProcessName":["dllhost"]},{"Handles":["285"],"NPM(K)":["16"],"PM(K)":["19356"],"WS(K)":["6808"],"CPU(s)":["0.80"],"Id":["11688"],"SI":["6"],"ProcessName":["msedge"]},{"Handles":["270"],"NPM(K)":["16"],"PM(K)":["23544"],"WS(K)":["6844"],"CPU(s)":["0.83"],"Id":["14820"],"SI":["6"],"ProcessName":["msedge"]},{"Handles":["320"],"NPM(K)":["16"],"PM(K)":["24768"],"WS(K)":["7340"],"CPU(s)":["0.88"],"Id":["1292"],"SI":["6"],"ProcessName":["msedge"]},{"Handles":["276"],"NPM(K)":["16"],"PM(K)":["19280"],"WS(K)":["6692"],"CPU(s)":["0.88"],"Id":["15008"],"SI":["6"],"ProcessName":["msedge"]},{"Handles":["420"],"NPM(K)":["26"],"PM(K)":["5416"],"WS(K)":["20600"],"CPU(s)":["0.92"],"Id":["14200"],"SI":["6"],"ProcessName":["svchost"]},{"Handles":["301"],"NPM(K)":["17"],"PM(K)":["21068"],"WS(K)":["7348"],"CPU(s)":["0.95"],"Id":["13684"],"SI":["6"],"ProcessName":["msedge"]},{"Handles":["319"],"NPM(K)":["17"],"PM(K)":["20912"],"WS(K)":["7456"],"CPU(s)":["1.08"],"Id":["3184"],"SI":["6"],"ProcessName":["msedge"]},{"Handles":["333"],"NPM(K)":["17"],"PM(K)":["25076"],"WS(K)":["7856"],"CPU(s)":["1.08"],"Id":["9328"],"SI":["6"],"ProcessName":["msedge"]},{"Handles":["255"],"NPM(K)":["14"],"PM(K)":["10376"],"WS(K)":["18900"],"CPU(s)":["1.08"],"Id":["9544"],"SI":["6"],"ProcessName":["msedge"]},{"Handles":["504"],"NPM(K)":["28"],"PM(K)":["59304"],"WS(K)":["51488"],"CPU(s)":["1.08"],"Id":["10900"],"SI":["6"],"ProcessName":["powershell"]},{"Handles":["319"],"NPM(K)":["18"],"PM(K)":["5284"],"WS(K)":["4108"],"CPU(s)":["1.14"],"Id":["8540"],"SI":["6"],"ProcessName":["HostAppServiceUpdater"]},{"Handles":["339"],"NPM(K)":["20"],"PM(K)":["6800"],"WS(K)":["29996"],"CPU(s)":["1.22"],"Id":["5944"],"SI":["6"],"ProcessName":["RuntimeBroker"]},{"Handles":["616"],"NPM(K)":["30"],"PM(K)":["53812"],"WS(K)":["61528"],"CPU(s)":["1.27"],"Id":["16996"],"SI":["6"],"ProcessName":["powershell"]},{"Handles":["295"],"NPM(K)":["19"],"PM(K)":["7372"],"WS(K)":["15280"],"CPU(s)":["1.28"],"Id":["13860"],"SI":["6"],"ProcessName":["gjagent"]},{"Handles":["183"],"NPM(K)":["18"],"PM(K)":["18796"],"WS(K)":["35940"],"CPU(s)":["1.34"],"Id":["13528"],"SI":["6"],"ProcessName":["node"]},{"Handles":["182"],"NPM(K)":["26"],"PM(K)":["23940"],"WS(K)":["41284"],"CPU(s)":["1.39"],"Id":["16004"],"SI":["6"],"ProcessName":["node"]},{"Handles":["391"],"NPM(K)":["17"],"PM(K)":["25480"],"WS(K)":["8968"],"CPU(s)":["1.42"],"Id":["14600"],"SI":["6"],"ProcessName":["msedge"]},{"Handles":["381"],"NPM(K)":["23"],"PM(K)":["12296"],"WS(K)":["35184"],"CPU(s)":["1.52"],"Id":["9372"],"SI":["6"],"ProcessName":["ApplicationFrameHost"]},{"Handles":["303"],"NPM(K)":["37"],"PM(K)":["9368"],"WS(K)":["20064"],"CPU(s)":["1.53"],"Id":["9200"],"SI":["6"],"ProcessName":["taskhostw"]},{"Handles":["309"],"NPM(K)":["15"],"PM(K)":["3712"],"WS(K)":["21452"],"CPU(s)":["1.56"],"Id":["13368"],"SI":["6"],"ProcessName":["svchost"]},{"Handles":["818"],"NPM(K)":["25"],"PM(K)":["385096"],"WS(K)":["330868"],"CPU(s)":["1.619.48"],"Id":["5392"],"SI":["6"],"ProcessName":["Code"]},{"Handles":["305"],"NPM(K)":["16"],"PM(K)":["22444"],"WS(K)":["7932"],"CPU(s)":["1.67"],"Id":["6268"],"SI":["6"],"ProcessName":["msedge"]},{"Handles":["514"],"NPM(K)":["30"],"PM(K)":["16176"],"WS(K)":["6288"],"CPU(s)":["1.70"],"Id":["11460"],"SI":["6"],"ProcessName":["StorPSCTL"]},{"Handles":["327"],"NPM(K)":["18"],"PM(K)":["41972"],"WS(K)":["83720"],"CPU(s)":["1.86"],"Id":["17000"],"SI":["6"],"ProcessName":["msedge"]},{"Handles":["182"],"NPM(K)":["26"],"PM(K)":["24228"],"WS(K)":["40680"],"CPU(s)":["2.33"],"Id":["5420"],"SI":["6"],"ProcessName":["node"]},{"Handles":["587"],"NPM(K)":["28"],"PM(K)":["60960"],"WS(K)":["7960"],"CPU(s)":["2.36"],"Id":["12180"],"SI":["6"],"ProcessName":["ePowerButton_NB"]},{"Handles":["394"],"NPM(K)":["19"],"PM(K)":["32296"],"WS(K)":["10020"],"CPU(s)":["2.44"],"Id":["14040"],"SI":["6"],"ProcessName":["msedge"]},{"Handles":["607"],"NPM(K)":["35"],"PM(K)":["30328"],"WS(K)":["58652"],"CPU(s)":["2.48"],"Id":["14532"],"SI":["6"],"ProcessName":["Notepad"]},{"Handles":["551"],"NPM(K)":["24"],"PM(K)":["7876"],"WS(K)":["31360"],"CPU(s)":["2.58"],"Id":["12980"],"SI":["6"],"ProcessName":["RuntimeBroker"]},{"Handles":["629"],"NPM(K)":["24"],"PM(K)":["13336"],"WS(K)":["25004"],"CPU(s)":["2.66"],"Id":["604"],"SI":["6"],"ProcessName":["SDXHelper"]},{"Handles":["1218"],"NPM(K)":["65"],"PM(K)":["42180"],"WS(K)":["3000"],"CPU(s)":["2.75"],"Id":["10352"],"SI":["6"],"ProcessName":["SystemSettings"]},{"Handles":["194"],"NPM(K)":["13"],"PM(K)":["41344"],"WS(K)":["79108"],"CPU(s)":["2.80"],"Id":["6760"],"SI":["6"],"ProcessName":["Code"]},{"Handles":["154"],"NPM(K)":["14"],"PM(K)":["26412"],"WS(K)":["16340"],"CPU(s)":["2.81"],"Id":["6456"],"SI":["6"],"ProcessName":["esbuild"]},{"Handles":["282"],"NPM(K)":["17"],"PM(K)":["13924"],"WS(K)":["33732"],"CPU(s)":["2.98"],"Id":["6044"],"SI":["6"],"ProcessName":["GitHubDesktop"]},{"Handles":["315"],"NPM(K)":["19"],"PM(K)":["32820"],"WS(K)":["9980"],"CPU(s)":["3.44"],"Id":["15072"],"SI":["6"],"ProcessName":["msedge"]},{"Handles":["332"],"NPM(K)":["19"],"PM(K)":["50388"],"WS(K)":["101356"],"CPU(s)":["3.52"],"Id":["16288"],"SI":["6"],"ProcessName":["msedge"]},{"Handles":["433"],"NPM(K)":["19"],"PM(K)":["42244"],"WS(K)":["10080"],"CPU(s)":["3.70"],"Id":["8008"],"SI":["6"],"ProcessName":["msedge"]},{"Handles":["280"],"NPM(K)":["17"],"PM(K)":["11996"],"WS(K)":["2436"],"CPU(s)":["3.78"],"Id":["12636"],"SI":["6"],"ProcessName":["msedgewebview2"]},{"Handles":["368"],"NPM(K)":["18"],"PM(K)":["32184"],"WS(K)":["11380"],"CPU(s)":["3.81"],"Id":["15776"],"SI":["6"],"ProcessName":["msedge"]},{"Handles":["163"],"NPM(K)":["11"],"PM(K)":["2304"],"WS(K)":["9280"],"CPU(s)":["3.92"],"Id":["9984"],"SI":["6"],"ProcessName":["OpenConsole"]},{"Handles":["294"],"NPM(K)":["18"],"PM(K)":["14028"],"WS(K)":["34744"],"CPU(s)":["4.14"],"Id":["8204"],"SI":["6"],"ProcessName":["Code"]},{"Handles":["440"],"NPM(K)":["21"],"PM(K)":["62836"],"WS(K)":["11444"],"CPU(s)":["4.27"],"Id":["12632"],"SI":["6"],"ProcessName":["msedge"]},{"Handles":["884"],"NPM(K)":["43"],"PM(K)":["31132"],"WS(K)":["81108"],"CPU(s)":["4.36"],"Id":["3400"],"SI":["6"],"ProcessName":["StartMenuExperienceHost"]},{"Handles":["704"],"NPM(K)":["29"],"PM(K)":["114300"],"WS(K)":["115096"],"CPU(s)":["4.56"],"Id":["13836"],"SI":["6"],"ProcessName":["GitHubDesktop"]},{"Handles":["796"],"NPM(K)":["35"],"PM(K)":["15144"],"WS(K)":["51820"],"CPU(s)":["4.78"],"Id":["13044"],"SI":["6"],"ProcessName":["RuntimeBroker"]},{"Handles":["520"],"NPM(K)":["23"],"PM(K)":["8600"],"WS(K)":["33864"],"CPU(s)":["5.89"],"Id":["12004"],"SI":["6"],"ProcessName":["svchost"]},{"Handles":["552"],"NPM(K)":["18"],"PM(K)":["45272"],"WS(K)":["11348"],"CPU(s)":["6.67"],"Id":["10984"],"SI":["6"],"ProcessName":["msedge"]},{"Handles":["1016"],"NPM(K)":["47"],"PM(K)":["33572"],"WS(K)":["64744"],"CPU(s)":["6.83"],"Id":["9148"],"SI":["6"],"ProcessName":["ShellExperienceHost"]},{"Handles":["851"],"NPM(K)":["28"],"PM(K)":["8068"],"WS(K)":["38372"],"CPU(s)":["7.34"],"Id":["7536"],"SI":["6"],"ProcessName":["SystemSettingsBroker"]},{"Handles":["428"],"NPM(K)":["20"],"PM(K)":["60784"],"WS(K)":["11556"],"CPU(s)":["7.78"],"Id":["7196"],"SI":["6"],"ProcessName":["msedge"]},{"Handles":["397"],"NPM(K)":["19"],"PM(K)":["76512"],"WS(K)":["132116"],"CPU(s)":["7.78"],"Id":["7668"],"SI":["6"],"ProcessName":["msedge"]},{"Handles":["735"],"NPM(K)":["30"],"PM(K)":["8432"],"WS(K)":["40216"],"CPU(s)":["8.02"],"Id":["13884"],"SI":["6"],"ProcessName":["Widgets"]},{"Handles":["609"],"NPM(K)":["19"],"PM(K)":["6560"],"WS(K)":["31900"],"CPU(s)":["8.63"],"Id":["6712"],"SI":["6"],"ProcessName":["sihost"]},{"Handles":["672"],"NPM(K)":["33"],"PM(K)":["221096"],"WS(K)":["104580"],"CPU(s)":["8.92"],"Id":["10236"],"SI":["6"],"ProcessName":["msedgewebview2"]},{"Handles":["389"],"NPM(K)":["21"],"PM(K)":["49084"],"WS(K)":["12840"],"CPU(s)":["9.25"],"Id":["10096"],"SI":["6"],"ProcessName":["msedge"]},{"Handles":["385"],"NPM(K)":["24"],"PM(K)":["87480"],"WS(K)":["18720"],"CPU(s)":["9.58"],"Id":["13008"],"SI":["6"],"ProcessName":["msedge"]},{"Handles":["1164"],"NPM(K)":["41"],"PM(K)":["33144"],"WS(K)":["15676"],"CPU(s)":["10.03"],"Id":["3244"],"SI":["6"],"ProcessName":["msedgewebview2"]},{"Handles":["255"],"NPM(K)":["17"],"PM(K)":["46920"],"WS(K)":["70508"],"CPU(s)":["11.81"],"Id":["480"],"SI":["6"],"ProcessName":["Code"]},{"Handles":["460"],"NPM(K)":["44"],"PM(K)":["60304"],"WS(K)":["95468"],"CPU(s)":["11.83"],"Id":["8912"],"SI":["6"],"ProcessName":["GitHubDesktop"]},{"Handles":["186"],"NPM(K)":["15"],"PM(K)":["36512"],"WS(K)":["68852"],"CPU(s)":["12.69"],"Id":["7868"],"SI":["6"],"ProcessName":["Code"]},{"Handles":["359"],"NPM(K)":["19"],"PM(K)":["41880"],"WS(K)":["21224"],"CPU(s)":["13.78"],"Id":["4496"],"SI":["6"],"ProcessName":["msedge"]},{"Handles":["816"],"NPM(K)":["32"],"PM(K)":["32400"],"WS(K)":["72444"],"CPU(s)":["15.25"],"Id":["11712"],"SI":["6"],"ProcessName":["GitHubDesktop"]},{"Handles":["312"],"NPM(K)":["16"],"PM(K)":["37980"],"WS(K)":["71368"],"CPU(s)":["17.00"],"Id":["15476"],"SI":["6"],"ProcessName":["msedge"]},{"Handles":["191"],"NPM(K)":["13"],"PM(K)":["73200"],"WS(K)":["75896"],"CPU(s)":["17.11"],"Id":["12176"],"SI":["6"],"ProcessName":["Code"]},{"Handles":["496"],"NPM(K)":["20"],"PM(K)":["11480"],"WS(K)":["32336"],"CPU(s)":["17.58"],"Id":["13548"],"SI":["6"],"ProcessName":["svchost"]},{"Handles":["205"],"NPM(K)":["14"],"PM(K)":["39688"],"WS(K)":["61528"],"CPU(s)":["17.84"],"Id":["4396"],"SI":["6"],"ProcessName":["Code"]},{"Handles":["330"],"NPM(K)":["24"],"PM(K)":["23636"],"WS(K)":["22500"],"CPU(s)":["18.78"],"Id":["12112"],"SI":["6"],"ProcessName":["CodeSetup-stable-6261075646f055b99068d3688932416f2346dd3b.tmp"]},{"Handles":["267"],"NPM(K)":["77"],"PM(K)":["75748"],"WS(K)":["91692"],"CPU(s)":["22.48"],"Id":["14460"],"SI":["6"],"ProcessName":["node"]},{"Handles":["393"],"NPM(K)":["19"],"PM(K)":["57804"],"WS(K)":["86752"],"CPU(s)":["22.50"],"Id":["8968"],"SI":["6"],"ProcessName":["Code"]},{"Handles":["1021"],"NPM(K)":["51"],"PM(K)":["73172"],"WS(K)":["8788"],"CPU(s)":["24.73"],"Id":["9728"],"SI":["6"],"ProcessName":["ACCStd"]},{"Handles":["442"],"NPM(K)":["20"],"PM(K)":["66632"],"WS(K)":["13588"],"CPU(s)":["26.03"],"Id":["14976"],"SI":["6"],"ProcessName":["msedge"]},{"Handles":["1704"],"NPM(K)":["173"],"PM(K)":["232284"],"WS(K)":["114524"],"CPU(s)":["27.42"],"Id":["4468"],"SI":["6"],"ProcessName":["SearchHost"]},{"Handles":["436"],"NPM(K)":["73"],"PM(K)":["24492"],"WS(K)":["35728"],"CPU(s)":["30.31"],"Id":["4736"],"SI":["6"],"ProcessName":["AppMonitorPlugIn"]},{"Handles":["744"],"NPM(K)":["34"],"PM(K)":["21712"],"WS(K)":["61084"],"CPU(s)":["34.31"],"Id":["13396"],"SI":["6"],"ProcessName":["TextInputHost"]},{"Handles":["685"],"NPM(K)":["43"],"PM(K)":["43580"],"WS(K)":["83264"],"CPU(s)":["39.98"],"Id":["3388"],"SI":["6"],"ProcessName":["WindowsTerminal"]},{"Handles":["195"],"NPM(K)":["14"],"PM(K)":["61456"],"WS(K)":["103908"],"CPU(s)":["41.50"],"Id":["14208"],"SI":["6"],"ProcessName":["Code"]},{"Handles":["357"],"NPM(K)":["18"],"PM(K)":["106644"],"WS(K)":["18296"],"CPU(s)":["43.16"],"Id":["11164"],"SI":["6"],"ProcessName":["msedgewebview2"]},{"Handles":["969"],"NPM(K)":["19"],"PM(K)":["113476"],"WS(K)":["118396"],"CPU(s)":["47.16"],"Id":["5276"],"SI":["6"],"ProcessName":["msedge"]},{"Handles":["330"],"NPM(K)":["18"],"PM(K)":["70548"],"WS(K)":["118136"],"CPU(s)":["57.58"],"Id":["11708"],"SI":["6"],"ProcessName":["msedge"]},{"Handles":["446"],"NPM(K)":["38"],"PM(K)":["34104"],"WS(K)":["56996"],"CPU(s)":["63.11"],"Id":["3632"],"SI":["6"],"ProcessName":["msedge"]},{"Handles":["187"],"NPM(K)":["13"],"PM(K)":["73392"],"WS(K)":["116848"],"CPU(s)":["66.75"],"Id":["2572"],"SI":["6"],"ProcessName":["Code"]},{"Handles":["473"],"NPM(K)":["16"],"PM(K)":["4856"],"WS(K)":["21452"],"CPU(s)":["69.45"],"Id":["2988"],"SI":["6"],"ProcessName":["ctfmon"]},{"Handles":["542"],"NPM(K)":["19"],"PM(K)":["147900"],"WS(K)":["198688"],"CPU(s)":["77.95"],"Id":["9852"],"SI":["6"],"ProcessName":["msedge"]},{"Handles":["370"],"NPM(K)":["20"],"PM(K)":["50620"],"WS(K)":["87404"],"CPU(s)":["115.91"],"Id":["4896"],"SI":["6"],"ProcessName":["msedge"]},{"Handles":["296"],"NPM(K)":["21"],"PM(K)":["102160"],"WS(K)":["112212"],"CPU(s)":["151.91"],"Id":["12748"],"SI":["6"],"ProcessName":["Code"]},{"Handles":["995"],"NPM(K)":["41"],"PM(K)":["47632"],"WS(K)":["92216"],"CPU(s)":["263.13"],"Id":["7720"],"SI":["6"],"ProcessName":["Code"]},{"Handles":["3956"],"NPM(K)":["135"],"PM(K)":["180052"],"WS(K)":["205652"],"CPU(s)":["282.38"],"Id":["8224"],"SI":["6"],"ProcessName":["explorer"]},{"Handles":["1607"],"NPM(K)":["77"],"PM(K)":["630548"],"WS(K)":["414188"],"CPU(s)":["371.47"],"Id":["11792"],"SI":["6"],"ProcessName":["msedge"]},{"Handles":["216"],"NPM(K)":["14"],"PM(K)":["163728"],"WS(K)":["184704"],"CPU(s)":["420.98"],"Id":["12192"],"SI":["6"],"ProcessName":["Code"]},{"Handles":["739"],"NPM(K)":["32"],"PM(K)":["214832"],"WS(K)":["164792"],"CPU(s)":["451.67"],"Id":["10260"],"SI":["6"],"ProcessName":["Code"]},{"Handles":["3993"],"NPM(K)":["298"],"PM(K)":["184628"],"WS(K)":["302384"],"CPU(s)":["635.61"],"Id":["4944"],"SI":["6"],"ProcessName":["msedge"]},{"Handles":["187"],"NPM(K)":["13"],"PM(K)":["234472"],"WS(K)":["257672"],"CPU(s)":["775.44"],"Id":["8408"],"SI":["6"],"ProcessName":["Code"]}]